<?xml version="1.0" encoding="UTF-8" ?>
<issues>
	<issue id="0"
		   status="0"
		   type="1"
		   priority="2"
		   project="0"
		   build="0"
		   assignee="0"
		   creatDate="06.10.2012"
		   creater="1"
		   modifyDate="07.10.2012"
		   lastModifier="0"
		   resolution="0">
		<summary>
			Wrong display headers.
		</summary>
		<description>
			Lorem ipsum dolor sit amet, consectetuer adipiscing elit.
			Aenean commodo ligula eget dolor. Aenean massa.
			Cum sociis natoque penatibus et magnis dis parturient montes, nascetur ridiculus mus.
			Donec quam felis, ultricies nec, pellentesque eu, pretium quis, sem.
		</description>
		<comments>
			<comment id="0">
				First commet.
			</comment>
			<comment id="1">
				Second commet.
			</comment>
		</comments>
	</issue>
	
	<issue id="0"
		   status="0"
		   type="1"
		   priority="2"
		   project="0"
		   build="0"
		   assignee="0"
		   creatDate="06.10.2012"
		   creater="1"
		   modifyDate="07.10.2012"
		   lastModifier="0"
		   resolution="0">
		<summary>Nulla consequat massa.</summary>
		<description>Nulla consequat massa quis enim. Donec pede justo, fringilla vel, aliquet nec, vulputate eget, arcu. In enim justo, rhoncus ut, imperdiet a, venenatis vitae, justo. </description>
		<comments>
			<comment id="0">
				First commet.
			</comment>
			<comment id="1">
				Second commet.
			</comment>
		</comments>
	</issue>
	<issue id="0"
		   status="0"
		   type="1"
		   priority="2"
		   project="0"
		   build="0"
		   assignee="0"
		   creatDate="06.10.2012"
		   creater="1"
		   modifyDate="07.10.2012"
		   lastModifier="0"
		   resolution="0">
		<summary>Aenean leo ligula, porttitor eu.</summary>
		<description>Aenean leo ligula, porttitor eu, consequat vitae, eleifend ac, enim. Aliquam lorem ante, dapibus in, viverra quis, feugiat a, tellus. Phasellus viverra nulla ut metus varius laoreet. Quisque rutrum. Aenean imperdiet. </description>
		<comments>
			<comment id="0">
				First commet.
			</comment>
			<comment id="1">
				Second commet.
			</comment>
		</comments>
	</issue>
	<issue id="0"
		   status="0"
		   type="1"
		   priority="2"
		   project="0"
		   build="0"
		   assignee="0"
		   creatDate="06.10.2012"
		   creater="1"
		   modifyDate="07.10.2012"
		   lastModifier="0"
		   resolution="0">
		<summary>Nam quam nunc, blandit vel, luctus pulvinar.</summary>
		<description>Nam quam nunc, blandit vel, luctus pulvinar, hendrerit id, lorem. Maecenas nec odio et ante tincidunt tempus. Donec vitae sapien ut libero venenatis faucibus. Nullam quis ante.</description>
		<comments>
			<comment id="0">
				First commet.
			</comment>
			<comment id="1">
				Second commet.
			</comment>
		</comments>
	</issue>
	<issue id="0"
		   status="0"
		   type="1"
		   priority="2"
		   project="0"
		   build="0"
		   assignee="0"
		   creatDate="06.10.2012"
		   creater="1"
		   modifyDate="07.10.2012"
		   lastModifier="0"
		   resolution="0">
		<summary>Etiam sit amet orci eget eros faucibus</summary>
		<description>Etiam sit amet orci eget eros faucibus tincidunt. Duis leo. Sed fringilla mauris sit amet nibh. Donec sodales sagittis magna. Sed consequat, leo eget bibendum sodales, augue velit cursus nunc.</description>
		<comments>
			<comment id="0">
				First commet.
			</comment>
			<comment id="1">
				Second commet.
			</comment>
		</comments>
	</issue>
	<issue id="0"
		   status="0"
		   type="1"
		   priority="2"
		   project="0"
		   build="0"
		   assignee="0"
		   creatDate="06.10.2012"
		   creater="1"
		   modifyDate="07.10.2012"
		   lastModifier="0"
		   resolution="0">
		<summary>Tiam sit amet orci eget eros faucibus tincidunt. Duis leo.</summary>
		<description>Etiam sit amet orci eget eros faucibus tincidunt. Duis leo. Sed fringilla mauris sit amet nibh. Donec sodales sagittis magna. Sed consequat, leo eget bibendum sodales, augue velit cursus nunc.</description>
		<comments>
			<comment id="0">
				First commet.
			</comment>
			<comment id="1">
				Second commet.
			</comment>
		</comments>
	</issue>
	<issue id="0"
		   status="0"
		   type="1"
		   priority="2"
		   project="0"
		   build="0"
		   assignee="0"
		   creatDate="06.10.2012"
		   creater="1"
		   modifyDate="07.10.2012"
		   lastModifier="0"
		   resolution="0">
		<summary> Lorem ipsum dolor sit amet, consectetur adipiscing elit.</summary>
		<description>Curabitur lacinia molestie mauris, vel adipiscing sapien suscipit sit amet. Proin tellus ante, condimentum a laoreet nec, adipiscing id magna. Proin vitae auctor purus. Cras non elit purus, vel vehicula lacus. Integer non massa nec mauris volutpat feugiat id at arcu.</description>
		<comments>
			<comment id="0">
				First commet.
			</comment>
			<comment id="1">
				Second commet.
			</comment>
		</comments>
	</issue>
	<issue id="0"
		   status="0"
		   type="1"
		   priority="2"
		   project="0"
		   build="0"
		   assignee="0"
		   creatDate="06.10.2012"
		   creater="1"
		   modifyDate="07.10.2012"
		   lastModifier="0"
		   resolution="0">
		<summary> Phasellus at nisi varius dolor iaculis molestie non sit amet risus.</summary>
		<description>Maecenas non lacus vel leo luctus lobortis vel non nulla. Aliquam erat volutpat. In ac risus tortor. Sed nibh turpis, euismod sit amet hendrerit nec, porta ac tellus. Praesent congue, erat quis pulvinar rutrum, sapien ipsum placerat dui, ac ultricies dolor quam et mi. Cras mi diam, elementum in laoreet a, malesuada sit amet est. Nullam suscipit velit nec est lacinia id adipiscing arcu ornare.
</description>
		<comments>
			<comment id="0">
				First commet.
			</comment>
			<comment id="1">
				Second commet.
			</comment>
		</comments>
	</issue>
	<issue id="0"
		   status="0"
		   type="1"
		   priority="2"
		   project="0"
		   build="0"
		   assignee="0"
		   creatDate="06.10.2012"
		   creater="1"
		   modifyDate="07.10.2012"
		   lastModifier="0"
		   resolution="0">
		<summary> In aliquam, dui et gravida ullamcorper.</summary>
		<description> In consequat, diam eu tincidunt gravida, orci dui porta libero, nec interdum tortor lorem vitae lacus. Curabitur ante nibh, consequat non iaculis a, ultrices vel quam. Donec tincidunt ultrices enim, quis elementum velit feugiat molestie. Lorem ipsum dolor sit amet, consectetur adipiscing elit. Mauris bibendum tortor ut libero commodo et ornare lectus tristique. Morbi eget eleifend mauris.</description>
		<comments>
			<comment id="0">
				First commet.
			</comment>
			<comment id="1">
				Second commet.
			</comment>
		</comments>
	</issue>
	<issue id="0"
		   status="0"
		   type="1"
		   priority="2"
		   project="0"
		   build="0"
		   assignee="0"
		   creatDate="06.10.2012"
		   creater="1"
		   modifyDate="07.10.2012"
		   lastModifier="0"
		   resolution="0">
		<summary>Lorem ipsum dolor sit amet.</summary>
		<description>
			Lorem ipsum dolor sit amet, consectetuer adipiscing elit.
			Aenean commodo ligula eget dolor. Aenean massa.
			Cum sociis natoque penatibus et magnis dis parturient montes, nascetur ridiculus mus.
			Donec quam felis, ultricies nec, pellentesque eu, pretium quis, sem.
		</description>
		<comments>
			<comment id="0">
				First commet.
			</comment>
			<comment id="1">
				Second commet.
			</comment>
		</comments>
	</issue>
	<issue id="0"
		   status="0"
		   type="1"
		   priority="2"
		   project="0"
		   build="0"
		   assignee="0"
		   creatDate="06.10.2012"
		   creater="1"
		   modifyDate="07.10.2012"
		   lastModifier="0"
		   resolution="0">
		<summary> Donec sit amet dui eget.</summary>
		<description>Donec sit amet dui eget ipsum rhoncus pellentesque nec eget felis. Sed non lorem lacus. Duis rhoncus leo eget urna malesuada vel rutrum ipsum elementum. Sed facilisis ornare nunc, vel euismod elit interdum sed. Nunc feugiat lobortis tellus, a tincidunt ipsum laoreet sed.</description>
		<comments>
			<comment id="0">
				First commet.
			</comment>
			<comment id="1">
				Second commet.
			</comment>
		</comments>
	</issue>
	<issue id="0"
		   status="0"
		   type="1"
		   priority="2"
		   project="0"
		   build="0"
		   assignee="0"
		   creatDate="06.10.2012"
		   creater="1"
		   modifyDate="07.10.2012"
		   lastModifier="0"
		   resolution="0">
		<summary> Maecenas dui orci.</summary>
		<description> Maecenas dui orci, feugiat et aliquet a, ornare ut quam. Donec rhoncus sollicitudin sagittis. Ut rutrum ligula vitae est molestie non condimentum magna tincidunt. Suspendisse gravida pulvinar augue et aliquam. Sed tincidunt lacus ac metus molestie quis interdum urna fringilla.</description>
		<comments>
			<comment id="0">
				First commet.
			</comment>
			<comment id="1">
				Second commet.
			</comment>
		</comments>
	</issue>
	<issue id="0"
		   status="0"
		   type="1"
		   priority="2"
		   project="0"
		   build="0"
		   assignee="0"
		   creatDate="06.10.2012"
		   creater="1"
		   modifyDate="07.10.2012"
		   lastModifier="0"
		   resolution="0">
		<summary>Maecenas dui orci.</summary>
		<description>Maecenas dui orci, feugiat et aliquet a, ornare ut quam. Donec rhoncus sollicitudin sagittis. Ut rutrum ligula vitae est molestie non condimentum magna tincidunt. Suspendisse gravida pulvinar augue et aliquam. Sed tincidunt lacus ac metus molestie quis interdum urna fringilla.</description>
		<comments>
			<comment id="0">
				First commet.
			</comment>
			<comment id="1">
				Second commet.
			</comment>
		</comments>
	</issue>
	<issue id="0"
		   status="0"
		   type="1"
		   priority="2"
		   project="0"
		   build="0"
		   assignee="0"
		   creatDate="06.10.2012"
		   creater="1"
		   modifyDate="07.10.2012"
		   lastModifier="0"
		   resolution="0">
		<summary>Nullam eleifend turpis nisi.</summary>
		<description>Nullam eleifend turpis nisi, eget consectetur augue. Sed et nunc massa. Integer consequat massa sit amet felis suscipit eu accumsan magna mollis. Nunc fermentum mattis fermentum. Fusce nibh orci, blandit vitae bibendum at, malesuada eu massa.</description>
		<comments>
			<comment id="0">
				First commet.
			</comment>
			<comment id="1">
				Second commet.
			</comment>
		</comments>
	</issue>
	<issue id="0"
		   status="0"
		   type="1"
		   priority="2"
		   project="0"
		   build="0"
		   assignee="0"
		   creatDate="06.10.2012"
		   creater="1"
		   modifyDate="07.10.2012"
		   lastModifier="0"
		   resolution="0">
		<summary>Vivamus leo sem.</summary>
		<description>Vivamus leo sem, interdum quis sollicitudin eget, placerat at quam. Aliquam erat volutpat. Curabitur bibendum quam velit, quis ultricies elit. Duis dapibus nulla eget enim auctor rutrum. Quisque ligula metus, blandit non porttitor eget, lacinia et est.</description>
		<comments>
			<comment id="0">
				First commet.
			</comment>
			<comment id="1">
				Second commet.
			</comment>
		</comments>
	</issue>
</issues>